[
        {
            "value": "Appleton",
            "label": "A"
        },
        {
            "value": "Argentia",
            "label": "A"
        },
        {
            "value": "Arnold`sCove",
            "label": "A"
        },
        {
            "value": "Avondale",
            "label": "A"
        },
        {
            "value": "Badger",
            "label": "B"
        },
        {
            "value": "BaieVerte",
            "label": "B"
        },
        {
            "value": "Batteau",
            "label": "B"
        },
        {
            "value": "BattleHarbour",
            "label": "B"
        },
        {
            "value": "Bauline",
            "label": "B"
        },
        {
            "value": "BayBulls",
            "label": "B"
        },
        {
            "value": "BaydeVerde",
            "label": "B"
        },
        {
            "value": "BayL`Argent",
            "label": "B"
        },
        {
            "value": "BayRoberts",
            "label": "B"
        },
        {
            "value": "Beaumont",
            "label": "B"
        },
        {
            "value": "BellIsland",
            "label": "B"
        },
        {
            "value": "Belleoram",
            "label": "B"
        },
        {
            "value": "Bellevue",
            "label": "B"
        },
        {
            "value": "Benoit`sCove",
            "label": "B"
        },
        {
            "value": "BirchyBay",
            "label": "B"
        },
        {
            "value": "Bishop`sFalls",
            "label": "B"
        },
        {
            "value": "BlackDuckCove",
            "label": "B"
        },
        {
            "value": "BlackTickle",
            "label": "B"
        },
        {
            "value": "Bonavista",
            "label": "B"
        },
        {
            "value": "Botwood",
            "label": "B"
        },
        {
            "value": "Boyd`sCove",
            "label": "B"
        },
        {
            "value": "Branch",
            "label": "B"
        },
        {
            "value": "Brent`sCove",
            "label": "B"
        },
        {
            "value": "Brigus",
            "label": "B"
        },
        {
            "value": "Buchans",
            "label": "B"
        },
        {
            "value": "Burgeo",
            "label": "B"
        },
        {
            "value": "Burin",
            "label": "B"
        },
        {
            "value": "Burlington",
            "label": "B"
        },
        {
            "value": "BurntIslands",
            "label": "B"
        },
        {
            "value": "Campbellton",
            "label": "C"
        },
        {
            "value": "CapeBroyle",
            "label": "C"
        },
        {
            "value": "Carbonear",
            "label": "C"
        },
        {
            "value": "Carmanville",
            "label": "C"
        },
        {
            "value": "Cartwright",
            "label": "C"
        },
        {
            "value": "Catalina",
            "label": "C"
        },
        {
            "value": "Centreville-Wareham-Trinity",
            "label": "C"
        },
        {
            "value": "ChanceCove",
            "label": "C"
        },
        {
            "value": "Changeislands",
            "label": "C"
        },
        {
            "value": "ChapelArm",
            "label": "C"
        },
        {
            "value": "Charlottetown",
            "label": "C"
        },
        {
            "value": "ChurchillFalls",
            "label": "C"
        },
        {
            "value": "Clarenville",
            "label": "C"
        },
        {
            "value": "Clarenville-ShoalHarbour",
            "label": "C"
        },
        {
            "value": "Clarke`sBeach",
            "label": "C"
        },
        {
            "value": "Codroy",
            "label": "C"
        },
        {
            "value": "Colliers",
            "label": "C"
        },
        {
            "value": "ComeByChance",
            "label": "C"
        },
        {
            "value": "ComfortCove-Newstead",
            "label": "C"
        },
        {
            "value": "ConceptionBaySouth",
            "label": "C"
        },
        {
            "value": "ConceptionHarbour",
            "label": "C"
        },
        {
            "value": "Conche",
            "label": "C"
        },
        {
            "value": "ConneRiver",
            "label": "C"
        },
        {
            "value": "Cook`sHarbour",
            "label": "C"
        },
        {
            "value": "CornerBrook",
            "label": "C"
        },
        {
            "value": "Cottlesville",
            "label": "C"
        },
        {
            "value": "CowHead",
            "label": "C"
        },
        {
            "value": "Cupids",
            "label": "C"
        },
        {
            "value": "Daniel`sHarbour",
            "label": "D"
        },
        {
            "value": "DavisInlet",
            "label": "D"
        },
        {
            "value": "DeerLake",
            "label": "D"
        },
        {
            "value": "Dover",
            "label": "D"
        },
        {
            "value": "Eastport",
            "label": "E"
        },
        {
            "value": "Elliston",
            "label": "E"
        },
        {
            "value": "Embree",
            "label": "E"
        },
        {
            "value": "Englee",
            "label": "E"
        },
        {
            "value": "EnglishHarbourEast",
            "label": "E"
        },
        {
            "value": "FairHaven",
            "label": "F"
        },
        {
            "value": "Fermeuse",
            "label": "F"
        },
        {
            "value": "Flatrock",
            "label": "F"
        },
        {
            "value": "FleurdeLys",
            "label": "F"
        },
        {
            "value": "Flower`sCove",
            "label": "F"
        },
        {
            "value": "Fogo",
            "label": "F"
        },
        {
            "value": "Forteau",
            "label": "F"
        },
        {
            "value": "Fortune",
            "label": "F"
        },
        {
            "value": "FoxCove-Mortier",
            "label": "F"
        },
        {
            "value": "FrenchmansIsland",
            "label": "F"
        },
        {
            "value": "Freshwater",
            "label": "F"
        },
        {
            "value": "Gambo",
            "label": "G"
        },
        {
            "value": "Gander",
            "label": "G"
        },
        {
            "value": "Garnish",
            "label": "G"
        },
        {
            "value": "Gaultois",
            "label": "G"
        },
        {
            "value": "Glenwood",
            "label": "G"
        },
        {
            "value": "Glovertown",
            "label": "G"
        },
        {
            "value": "GooseBay",
            "label": "G"
        },
        {
            "value": "GrandBank",
            "label": "G"
        },
        {
            "value": "GrandFalls",
            "label": "G"
        },
        {
            "value": "GrandFalls-Windsor",
            "label": "G"
        },
        {
            "value": "GreatHarbourDeep",
            "label": "G"
        },
        {
            "value": "GreenIslandCove",
            "label": "G"
        },
        {
            "value": "Greenspond",
            "label": "G"
        },
        {
            "value": "Hampden",
            "label": "H"
        },
        {
            "value": "Hant`sHarbour",
            "label": "H"
        },
        {
            "value": "HappyValley-GooseBay",
            "label": "H"
        },
        {
            "value": "HarbourBreton",
            "label": "H"
        },
        {
            "value": "HarbourGrace",
            "label": "H"
        },
        {
            "value": "HarbourMain-ChapelCove-Lakev",
            "label": "H"
        },
        {
            "value": "HareBay",
            "label": "H"
        },
        {
            "value": "Hawke`sBay",
            "label": "H"
        },
        {
            "value": "Heart`sContent",
            "label": "H"
        },
        {
            "value": "Heart`sDelight-Islington",
            "label": "H"
        },
        {
            "value": "Heart`sDesire",
            "label": "H"
        },
        {
            "value": "Hickman`sHarbour",
            "label": "H"
        },
        {
            "value": "Hillgrade",
            "label": "H"
        },
        {
            "value": "Hillview",
            "label": "H"
        },
        {
            "value": "Holyrood",
            "label": "H"
        },
        {
            "value": "Hopedale",
            "label": "H"
        },
        {
            "value": "Howley",
            "label": "H"
        },
        {
            "value": "HumberArmSouth",
            "label": "H"
        },
        {
            "value": "IndianTickle",
            "label": "I"
        },
        {
            "value": "IslandHarbour",
            "label": "I"
        },
        {
            "value": "IsleauxMorts",
            "label": "I"
        },
        {
            "value": "Jackson`sArm",
            "label": "J"
        },
        {
            "value": "Jamestown",
            "label": "J"
        },
        {
            "value": "JoeBatt`sArm-Barr`dIslands-",
            "label": "J"
        },
        {
            "value": "King`sCove",
            "label": "K"
        },
        {
            "value": "King`sPoint",
            "label": "K"
        },
        {
            "value": "Kippens",
            "label": "K"
        },
        {
            "value": "L`Anse-au-Loup",
            "label": "L"
        },
        {
            "value": "LaScie",
            "label": "L"
        },
        {
            "value": "LabradorCity",
            "label": "L"
        },
        {
            "value": "LadleCove",
            "label": "L"
        },
        {
            "value": "Lamaline",
            "label": "L"
        },
        {
            "value": "LarkHarbour",
            "label": "L"
        },
        {
            "value": "Lawn",
            "label": "L"
        },
        {
            "value": "Lewisporte",
            "label": "L"
        },
        {
            "value": "LittleBay",
            "label": "L"
        },
        {
            "value": "LittleBayIslands",
            "label": "L"
        },
        {
            "value": "LittleBurntBay",
            "label": "L"
        },
        {
            "value": "LittleCatalina",
            "label": "L"
        },
        {
            "value": "LittleHeart`sEase",
            "label": "L"
        },
        {
            "value": "LogyBay-MiddleCove-OuterCov",
            "label": "L"
        },
        {
            "value": "LongHarbour-MountArlingtonH",
            "label": "L"
        },
        {
            "value": "LongPond",
            "label": "L"
        },
        {
            "value": "Lourdes",
            "label": "L"
        },
        {
            "value": "LowerIslandCove",
            "label": "L"
        },
        {
            "value": "Lumsden",
            "label": "L"
        },
        {
            "value": "MainBrook",
            "label": "M"
        },
        {
            "value": "Makkovik",
            "label": "M"
        },
        {
            "value": "Mary`sHarbour",
            "label": "M"
        },
        {
            "value": "Marystown",
            "label": "M"
        },
        {
            "value": "MasseyDrive",
            "label": "M"
        },
        {
            "value": "McIver`s",
            "label": "M"
        },
        {
            "value": "Millertown",
            "label": "M"
        },
        {
            "value": "Milltown-HeadofBayD`Espoir",
            "label": "M"
        },
        {
            "value": "Ming`sBight",
            "label": "M"
        },
        {
            "value": "Monkstown",
            "label": "M"
        },
        {
            "value": "MountCarmel-MitchellsBrook-S",
            "label": "M"
        },
        {
            "value": "MountMoriah",
            "label": "M"
        },
        {
            "value": "MountPearl",
            "label": "M"
        },
        {
            "value": "MusgraveHarbour",
            "label": "M"
        },
        {
            "value": "Musgravetown",
            "label": "M"
        },
        {
            "value": "Nain",
            "label": "N"
        },
        {
            "value": "NewHarbour",
            "label": "N"
        },
        {
            "value": "NewPerlican",
            "label": "N"
        },
        {
            "value": "New-Wes-Valley",
            "label": "N"
        },
        {
            "value": "NippersHarbour",
            "label": "N"
        },
        {
            "value": "Norman`sCove-LongCove",
            "label": "N"
        },
        {
            "value": "NorrisArm",
            "label": "N"
        },
        {
            "value": "NorthWestRiver",
            "label": "N"
        },
        {
            "value": "NorthernArm",
            "label": "N"
        },
        {
            "value": "OldPerlican",
            "label": "O"
        },
        {
            "value": "PacksHarbour",
            "label": "P"
        },
        {
            "value": "Pacquet",
            "label": "P"
        },
        {
            "value": "Paradise",
            "label": "P"
        },
        {
            "value": "ParadiseRiver",
            "label": "P"
        },
        {
            "value": "Pasadena",
            "label": "P"
        },
        {
            "value": "Peterview",
            "label": "P"
        },
        {
            "value": "PettyHarbour-MaddoxCove",
            "label": "P"
        },
        {
            "value": "Placentia",
            "label": "P"
        },
        {
            "value": "PlateCoveEast",
            "label": "P"
        },
        {
            "value": "PointLeamington",
            "label": "P"
        },
        {
            "value": "Pool`sCove",
            "label": "P"
        },
        {
            "value": "PortauChoix",
            "label": "P"
        },
        {
            "value": "PortauPortWest-Aguathuna-Fe",
            "label": "P"
        },
        {
            "value": "PortAuxBasques",
            "label": "P"
        },
        {
            "value": "PortBlandford",
            "label": "P"
        },
        {
            "value": "PortHopeSimpson",
            "label": "P"
        },
        {
            "value": "PortRexton",
            "label": "P"
        },
        {
            "value": "PortSaunders",
            "label": "P"
        },
        {
            "value": "PortUnion",
            "label": "P"
        },
        {
            "value": "PortugalCove-St.Philip`s",
            "label": "P"
        },
        {
            "value": "Postville",
            "label": "P"
        },
        {
            "value": "PouchCove",
            "label": "P"
        },
        {
            "value": "Princeton",
            "label": "P"
        },
        {
            "value": "Raleigh",
            "label": "R"
        },
        {
            "value": "Ramea",
            "label": "R"
        },
        {
            "value": "RedBay",
            "label": "R"
        },
        {
            "value": "ReefsHarbour",
            "label": "R"
        },
        {
            "value": "RencontreEast",
            "label": "R"
        },
        {
            "value": "Rigolet",
            "label": "R"
        },
        {
            "value": "RiverofPonds",
            "label": "R"
        },
        {
            "value": "Robert`sArm",
            "label": "R"
        },
        {
            "value": "RockyHarbour",
            "label": "R"
        },
        {
            "value": "Roddickton",
            "label": "R"
        },
        {
            "value": "RoseBlanche-HarbourLeCou",
            "label": "R"
        },
        {
            "value": "Rushoon",
            "label": "R"
        },
        {
            "value": "SalmonCove",
            "label": "S"
        },
        {
            "value": "Salvage",
            "label": "S"
        },
        {
            "value": "SealCove",
            "label": "S"
        },
        {
            "value": "Seldom-LittleSeldom",
            "label": "S"
        },
        {
            "value": "SmallPoint-BroadCove-Blackhe",
            "label": "S"
        },
        {
            "value": "SouthBrook",
            "label": "S"
        },
        {
            "value": "SouthRiver",
            "label": "S"
        },
        {
            "value": "SouthernHarbour",
            "label": "S"
        },
        {
            "value": "Spaniard`sBay",
            "label": "S"
        },
        {
            "value": "SpottedIsland",
            "label": "S"
        },
        {
            "value": "Springdale",
            "label": "S"
        },
        {
            "value": "St.Alban`s",
            "label": "S"
        },
        {
            "value": "St.Anthony",
            "label": "S"
        },
        {
            "value": "St.Bernard`s-JacquesFontaine",
            "label": "S"
        },
        {
            "value": "St.Brendan`s",
            "label": "S"
        },
        {
            "value": "St.Bride`s",
            "label": "S"
        },
        {
            "value": "St.George`s",
            "label": "S"
        },
        {
            "value": "St.Jacques-Coomb`sCove",
            "label": "S"
        },
        {
            "value": "St.John`s",
            "label": "S"
        },
        {
            "value": "St.Lawrence",
            "label": "S"
        },
        {
            "value": "St.Lewis",
            "label": "S"
        },
        {
            "value": "St.Lunaire-Griquet",
            "label": "S"
        },
        {
            "value": "St.Mary`s",
            "label": "S"
        },
        {
            "value": "St.Vincent`s-St.Stephen`s-Pe",
            "label": "S"
        },
        {
            "value": "SteadyBrook",
            "label": "S"
        },
        {
            "value": "Stephenville",
            "label": "S"
        },
        {
            "value": "StephenvilleCrossing",
            "label": "S"
        },
        {
            "value": "Summerford",
            "label": "S"
        },
        {
            "value": "Summerside",
            "label": "S"
        },
        {
            "value": "Sunnyside",
            "label": "S"
        },
        {
            "value": "TerraNova",
            "label": "T"
        },
        {
            "value": "Terrenceville",
            "label": "T"
        },
        {
            "value": "Torbay",
            "label": "T"
        },
        {
            "value": "Trepassey",
            "label": "T"
        },
        {
            "value": "Triton",
            "label": "T"
        },
        {
            "value": "TroutRiver",
            "label": "T"
        },
        {
            "value": "Twillingate",
            "label": "T"
        },
        {
            "value": "UpperIslandCove",
            "label": "U"
        },
        {
            "value": "Victoria",
            "label": "V"
        },
        {
            "value": "Wabana",
            "label": "W"
        },
        {
            "value": "Wabush",
            "label": "W"
        },
        {
            "value": "Wesleyville",
            "label": "W"
        },
        {
            "value": "WesternBay",
            "label": "W"
        },
        {
            "value": "Westport",
            "label": "W"
        },
        {
            "value": "Whitbourne",
            "label": "W"
        },
        {
            "value": "Winterton",
            "label": "W"
        },
        {
            "value": "WitlessBay",
            "label": "W"
        },
        {
            "value": "WoodyPoint",
            "label": "W"
        }
    ]